setup.py
django_hipster_api.egg-info/PKG-INFO
django_hipster_api.egg-info/SOURCES.txt
django_hipster_api.egg-info/dependency_links.txt
django_hipster_api.egg-info/not-zip-safe
django_hipster_api.egg-info/top_level.txt
hipster_api/__init__.py
hipster_api/settings.py
hipster_api/views.py
hipster_api/fields/__init__.py
hipster_api/fields/base.py
hipster_api/fields/number.py
hipster_api/fields/str.py
hipster_api/management/__init__.py
hipster_api/management/commands/__init__.py
hipster_api/management/commands/hipster_api_doc.py
hipster_api/management/helpers/__init__.py
hipster_api/management/helpers/create_html.py
hipster_api/management/helpers/get_dict.py
hipster_api/management/helpers/search_api.py