Metadata-Version: 1.1
Name: django-hipster-api
Version: 1.6.2
Summary: wrapper django rest framework
Home-page: https://github.com/RustoriaRu/hipster_api
Author: vir-mir
Author-email: virmir49@gmail.com
License: MIT
Keywords: django rest framework
Platform: UNKNOWN
Classifier: Environment :: Web Environment
Classifier: Intended Audience :: Developers
Classifier: License :: OSI Approved :: MIT License
Classifier: Programming Language :: Python :: 2.7
Classifier: Programming Language :: Python :: 3.3
Classifier: Programming Language :: Python :: 3.4
Classifier: Topic :: Software Development :: Libraries :: Python Modules
